nextcloud_tasks_api/__init__.py
nextcloud_tasks_api/api.py
nextcloud_tasks_api/cli/__init__.py
nextcloud_tasks_api/cli/__main__.py
nextcloud_tasks_api/cli/api.py
nextcloud_tasks_api/cli/cli.py
nextcloud_tasks_api/cli/config.py
nextcloud_tasks_api/cli/prompts.py
nextcloud_tasks_api/cli/task.py
nextcloud_tasks_api/error.py
nextcloud_tasks_api/ical/__init__.py
nextcloud_tasks_api/ical/ical.py
nextcloud_tasks_api/ical/task.py
nextcloud_tasks_api/parser.py
nextcloud_tasks_api/request.py
nextcloud_tasks_api/setup.py
nextcloud_tasks_api-0.0.5.dist-info/WHEEL
nextcloud_tasks_api-0.0.5.dist-info/METADATA
nextcloud_tasks_api-0.0.5.dist-info/licenses/LICENCE.txt
nextcloud_tasks_api-0.0.5.dist-info/RECORD
