Metadata-Version: 2.1
Name: nextcloud_tasks_api
Version: 0.0.5
Summary: A package to pilot the nextcloud Tasks API
Author-email: Hackitude42 <hackitude42@gmail.com>
Maintainer-email: Alban Crommer <pip@albancrommer.com>
Requires-Python: >=3.7
Classifier: License :: OSI Approved :: GNU Affero General Public License v3 or later (AGPLv3+)
Classifier: Operating System :: OS Independent
Classifier: Programming Language :: Python :: 3
Requires-Dist: questionary
Requires-Dist: requests
Project-URL: Bug Tracker, https://gitlab.com/albancrommer/nextcloud-tasks-api/-/issues
Project-URL: Homepage, https://gitlab.com/albancrommer/nextcloud-tasks-api
